mqtt_house/__about__.py
mqtt_house/__init__.py
mqtt_house/__main__.py
mqtt_house/settings.py
mqtt_house/util.py
mqtt_house/cli/__init__.py
mqtt_house/cli/device.py
mqtt_house/lib/__init__.py
mqtt_house/lib/install.py
mqtt_house/lib/ota.py
mqtt_house/micro/__init__.py
mqtt_house/micro/bme280_float.py
mqtt_house/micro/ds18x20.py
mqtt_house/micro/main.py
mqtt_house/micro/microdot.py
mqtt_house/micro/mqtt_as.py
mqtt_house/micro/onewire.py
mqtt_house/micro/ota_server.py
mqtt_house/micro/status_led.py
mqtt_house/micro/mqtt_house/__about__.py
mqtt_house/micro/mqtt_house/__init__.py
mqtt_house/micro/mqtt_house/sensors.py
mqtt_house/micro/mqtt_house/util.py
mqtt_house/micro/mqtt_house/device/__init__.py
mqtt_house/micro/mqtt_house/device/enviro.py
mqtt_house/micro/mqtt_house/device/generic.py
mqtt_house/micro/mqtt_house/entity/__init__.py
mqtt_house/micro/mqtt_house/entity/base.py
mqtt_house/micro/mqtt_house/entity/binary_sensor.py
mqtt_house/micro/mqtt_house/entity/display.py
mqtt_house/micro/mqtt_house/entity/humidity.py
mqtt_house/micro/mqtt_house/entity/pressure.py
mqtt_house/micro/mqtt_house/entity/switch.py
mqtt_house/micro/mqtt_house/entity/light/__init__.py
mqtt_house/micro/mqtt_house/entity/light/singlepinsimple.py
mqtt_house/micro/mqtt_house/entity/light/threepinrgb.py
mqtt_house/micro/mqtt_house/entity/luminosity/__init__.py
mqtt_house/micro/mqtt_house/entity/luminosity/ltr559.py
mqtt_house/micro/mqtt_house/entity/temperature/__init__.py
mqtt_house/micro/mqtt_house/entity/temperature/bme280.py
mqtt_house/micro/mqtt_house/entity/temperature/onewireds18x20.py
mqtt_house-0.0.3.dist-info/METADATA
mqtt_house-0.0.3.dist-info/WHEEL
mqtt_house-0.0.3.dist-info/entry_points.txt
mqtt_house-0.0.3.dist-info/licenses/LICENSE.txt
mqtt_house-0.0.3.dist-info/RECORD
