Metadata-Version: 2.4
Name: mqtt-house
Version: 0.0.3
Project-URL: Documentation, https://github.com/unknown/mqtt-house#readme
Project-URL: Issues, https://github.com/unknown/mqtt-house/issues
Project-URL: Source, https://github.com/unknown/mqtt-house
Author-email: Mark Hall <mark.hall@work.room3b.eu>
License-Expression: MIT
License-File: LICENSE.txt
Classifier: Development Status :: 4 - Beta
Classifier: Programming Language :: Python
Classifier: Programming Language :: Python :: 3.10
Classifier: Programming Language :: Python :: 3.11
Classifier: Programming Language :: Python :: Implementation :: CPython
Classifier: Programming Language :: Python :: Implementation :: PyPy
Requires-Python: >=3.10
Requires-Dist: fastapi[all]
Requires-Dist: httpx
Requires-Dist: pydantic<3,>=2
Requires-Dist: pyyaml<7,>=6
Requires-Dist: rshell
Requires-Dist: typer[all]
